EnergyPlus-OPC/EnergyPlusOPCBridge.py
EnergyPlus-OPC/OPCConfigBuilder.py
EnergyPlus-OPC/example_controller.py
EnergyPlus-OPC/openopc_connector.py
EnergyPlus-OPC/schedule_controller.py
EnergyPlus-OPC/ePlusBuildings/LargeHotel/Building.idf
EnergyPlus-OPC/ePlusBuildings/LargeHotel/Energy+.idd
EnergyPlus-OPC/ePlusBuildings/LargeHotel/In.idf
EnergyPlus-OPC/ePlusBuildings/LargeHotel/eplusout.audit
EnergyPlus-OPC/ePlusBuildings/LargeHotel/eplusout.bnd
EnergyPlus-OPC/ePlusBuildings/LargeHotel/eplusout.csv
EnergyPlus-OPC/ePlusBuildings/LargeHotel/eplusout.eio
EnergyPlus-OPC/ePlusBuildings/LargeHotel/eplusout.end
EnergyPlus-OPC/ePlusBuildings/LargeHotel/eplusout.err
EnergyPlus-OPC/ePlusBuildings/LargeHotel/eplusout.eso
EnergyPlus-OPC/ePlusBuildings/LargeHotel/eplusout.mtd
EnergyPlus-OPC/ePlusBuildings/LargeHotel/eplusout.mtr
EnergyPlus-OPC/ePlusBuildings/LargeHotel/eplusout.shd
EnergyPlus-OPC/ePlusBuildings/LargeHotel/eplusssz.csv
EnergyPlus-OPC/ePlusBuildings/LargeHotel/epluszsz.csv
EnergyPlus-OPC/ePlusBuildings/LargeHotel/in.epw
EnergyPlus-OPC/ePlusBuildings/LargeHotel/in.stat
EnergyPlus-OPC/ePlusBuildings/LargeHotel/readvars.audit
EnergyPlus-OPC/ePlusBuildings/LargeHotel/socket.cfg
EnergyPlus-OPC/ePlusBuildings/LargeHotel/sqlite.err
EnergyPlus-OPC/ePlusBuildings/LargeHotel/testsocket.log
EnergyPlus-OPC/ePlusBuildings/LargeHotel/utilSocket.log
EnergyPlus-OPC/ePlusBuildings/LargeHotel/variables.cfg
pyEp/SPtMasterTable_587017_2012_amy.epw
pyEp/__init__.py
pyEp/example.py
pyEp/pyEp.py
pyEp/pyEpError.py
pyEp/socket_builder.py
pyEp/EnergyPlus-OPC/EnergyPlusOPCBridge.py
pyEp/EnergyPlus-OPC/OPCConfigBuilder.py
pyEp/EnergyPlus-OPC/example_controller.py
pyEp/EnergyPlus-OPC/openopc_connector.py
pyEp/EnergyPlus-OPC/schedule_controller.py
pyEp/EnergyPlus-OPC/ePlusBuildings/LargeHotel/Building.idf
pyEp/EnergyPlus-OPC/ePlusBuildings/LargeHotel/In.idf
pyEp/EnergyPlus-OPC/ePlusBuildings/LargeHotel/in.epw
pyEp-0.9.4.dist-info/DESCRIPTION.rst
pyEp-0.9.4.dist-info/METADATA
pyEp-0.9.4.dist-info/RECORD
pyEp-0.9.4.dist-info/WHEEL
pyEp-0.9.4.dist-info/metadata.json
pyEp-0.9.4.dist-info/top_level.txt
