Metadata-Version: 2.0
Name: pyEp
Version: 0.9.4
Summary: pyEp: EnergyPlus cosimulation in Python
Home-page: UNKNOWN
Author: Derek Nong
Author-email: dnong@sas.upenn.edu
License: MIT
Keywords: EnergyPlus simulation
Platform: UNKNOWN
Classifier: Development Status :: 4 - Beta
Classifier: Intended Audience :: Science/Research
Classifier: License :: OSI Approved :: MIT License
Classifier: Programming Language :: Python :: 2.7
Classifier: Programming Language :: Python :: 3.5
